{
  "@context": "https://schema.org",
  "@type": "GovernmentService",
  "@id": "https://www.statelicensingreference.com/hawaii-ot",
  "identifier": "hawaii-ot",
  "name": "Hawaii Occupational Therapist License",
  "description": "Already licensed as an occupational therapist? Here's whether your license transfers to Hawaii - compact status, endorsement steps, fees, and processing time.",
  "url": "https://www.statelicensingreference.com/hawaii-ot",
  "provider": {
    "@type": "GovernmentOrganization",
    "name": "Hawaii DCCA Professional & Vocational Licensing — OT",
    "parentOrganization": "Hawaii Department of Health (DOH) Office of Health Care Assurance",
    "url": "https://cca.hawaii.gov/pvl/",
    "telephone": "(808) 586-3000",
    "faxNumber": "N/A (contact by phone)",
    "email": "pvl@dcca.hawaii.gov",
    "address": {
      "@type": "PostalAddress",
      "streetAddress": "See board website",
      "description": "DCCA, PVL Licensing Branch, P.O. Box 3469, Honolulu, HI 96801"
    }
  },
  "areaServed": {
    "@type": "State",
    "name": "Hawaii"
  },
  "serviceType": "Professional License",
  "category": "Occupational Therapist",
  "additionalType": "Occupational Therapist Registered (OTR)",
  "offers": [
    {
      "@type": "Offer",
      "name": "Initial Application Fee",
      "description": "N/A"
    },
    {
      "@type": "Offer",
      "name": "Renewal Fee",
      "description": "$150",
      "price": 150.0,
      "priceCurrency": "USD"
    }
  ],
  "processingTime": "4 to 8 Weeks",
  "licenseDuration": "2 Years",
  "renewalCycle": "Every 2 years (by June 30th of odd-numbered years)",
  "requiredDocuments": [
    {
      "name": "Official Transcripts",
      "description": "Sent directly from your educational institution."
    },
    {
      "name": "NBCOT Score Report",
      "description": "Official verification of passing the NBCOT exam."
    }
  ],
  "fingerprinting": {
    "required": true,
    "method_in_state": "LiveScan (IdentoGO)",
    "method_out_of_state": "IdentoGO Out-of-State Live Scan (adds ~$39.95 fee) OR FD-258 hard card via mail (tip: moisturize hands for days prior to reduce smudge rejects)",
    "vendor": "IdentoGO (IDEMIA)",
    "fee": "$35-$50 (varies by state)",
    "delay_out_of_state_weeks": "2-4",
    "vendor_url": "https://uenroll.identogo.com/"
  },
  "compactStatus": {
    "isCompactMember": false,
    "compactName": "OT Compact",
    "compactPrivilegeFee": "N/A"
  },
  "temporaryLicense": {
    "available": true,
    "fee": "See board",
    "processingTime": "See board",
    "duration": "See board"
  },
  "mainEntity": [
    {
      "@type": "Question",
      "name": "How much does a Hawaii OT license cost?",
      "acceptedAnswer": {
        "@type": "Answer",
        "text": "The total initial application and licensing fee is approximately $279. Check the board website for the latest fee schedule."
      }
    },
    {
      "@type": "Question",
      "name": "Is NBCOT certification required?",
      "acceptedAnswer": {
        "@type": "Answer",
        "text": "Yes, passing the NBCOT exam is a standard requirement for initial licensure across all states."
      }
    },
    {
      "@type": "Question",
      "name": "Does Hawaii have reciprocity for occupational therapists?",
      "acceptedAnswer": {
        "@type": "Answer",
        "text": "No interstate compact currently covers occupational therapist practice in Hawaii. To work in Hawaii, apply for licensure by endorsement through the state board."
      }
    },
    {
      "@type": "Question",
      "name": "How long does it take to transfer my occupational therapist license to Hawaii?",
      "acceptedAnswer": {
        "@type": "Answer",
        "text": "Most endorsement applications take 4 to 6 Weeks."
      }
    },
    {
      "@type": "Question",
      "name": "Can I start working in Hawaii while my endorsement application is processing?",
      "acceptedAnswer": {
        "@type": "Answer",
        "text": "A temporary or provisional credential is available while the full endorsement application is pending."
      }
    }
  ],
  "sourceMetadata": {
    "lastUpdated": "2026-02-25",
    "lastVerifiedDate": "2026-03-22",
    "boardSourceUrl": "https://cca.hawaii.gov/pvl/"
  }
}
